Metadata-Version: 2.1
Name: ezutil
Version: 0.0.2
Summary: Make software development eazy
Home-page: https://edgetoolkit.github.io/ezutil
Author: Mingyi Zhang
Author-email: mingyi.z@outlook.com
License: MIT
Platform: UNKNOWN
Classifier: Development Status :: 1 - Planning
Classifier: Intended Audience :: Developers
Classifier: Topic :: Software Development :: Build Tools
Classifier: License :: OSI Approved :: MIT License
Classifier: Programming Language :: Python :: 3
Classifier: Programming Language :: Python :: 3.6
License-File: LICENSE.md
